lab_orchestrator_lib_auth/__init__.py
lab_orchestrator_lib_auth/auth.py
lab_orchestrator_lib_auth-2.2.0.dist-info/LICENSE
lab_orchestrator_lib_auth-2.2.0.dist-info/METADATA
lab_orchestrator_lib_auth-2.2.0.dist-info/WHEEL
lab_orchestrator_lib_auth-2.2.0.dist-info/top_level.txt
lab_orchestrator_lib_auth-2.2.0.dist-info/RECORD
