Metadata-Version: 2.1
Name: lab-orchestrator-lib-auth
Version: 2.2.0
Summary: Authentication module for lab-orchestrator-lib.
Home-page: https://github.com/LabOrchestrator/LabOrchestratorLib-Auth
Author: Marco Schlicht
Author-email: git@privacymail.dev
License: Mozilla Public License 2.0 (MPL 2.0)
Project-URL: Bug Tracker, https://github.com/LabOrchestrator/LabOrchestratorLib-Auth/issues
Platform: UNKNOWN
Classifier: Programming Language :: Python :: 3
Classifier: License :: OSI Approved :: Mozilla Public License 2.0 (MPL 2.0)
Classifier: Operating System :: OS Independent
Classifier: Development Status :: 5 - Production/Stable
Requires-Python: >=3.8
License-File: LICENSE
Requires-Dist: PyJWT (==2.1.0)
